track_actions/__init__.py
track_actions/apps.py
track_actions/constants.py
track_actions/models.py
track_actions/requestMiddleware.py
track_actions/serializers.py
track_actions/signals.py
track_actions/urls.py
track_actions/views.py
track_actions/migrations/0001_initial.py
track_actions/migrations/0002_history_path.py
track_actions/migrations/__init__.py
drf_history-1.0.1.dist-info/LICENSE
drf_history-1.0.1.dist-info/METADATA
drf_history-1.0.1.dist-info/WHEEL
drf_history-1.0.1.dist-info/top_level.txt
drf_history-1.0.1.dist-info/RECORD
